server.py
mcp_requests-0.3.3.dist-info/licenses/LICENCE
mcp_requests-0.3.3.dist-info/METADATA
mcp_requests-0.3.3.dist-info/WHEEL
mcp_requests-0.3.3.dist-info/entry_points.txt
mcp_requests-0.3.3.dist-info/top_level.txt
mcp_requests-0.3.3.dist-info/RECORD
