Metadata-Version: 2.4
Name: mcp-requests
Version: 0.3.3
Summary: Un servidor MCP para realizar peticiones HTTP
Author-email: Alejandro Cuartas <alejandro.cuartas@yahoo.com>
License-Expression: MIT
Project-URL: Homepage, https://github.com/tuusuario/mcp-requests
Project-URL: Repository, https://github.com/tuusuario/mcp-requests
Project-URL: Issues, https://github.com/tuusuario/mcp-requests/issues
Keywords: mcp,model-context-protocol,http,requests
Classifier: Development Status :: 3 - Alpha
Classifier: Intended Audience :: Developers
Classifier: Programming Language :: Python :: 3
Classifier: Programming Language :: Python :: 3.8
Classifier: Programming Language :: Python :: 3.9
Classifier: Programming Language :: Python :: 3.10
Classifier: Programming Language :: Python :: 3.11
Classifier: Programming Language :: Python :: 3.12
Requires-Python: >=3.8
License-File: LICENCE
Requires-Dist: fastmcp>=2.0.0
Requires-Dist: requests>=2.25.0
Requires-Dist: pydantic>=2.0.0
Dynamic: license-file
